odoo/addons/crm_phonecall_timesheet/README.rst
odoo/addons/crm_phonecall_timesheet/__init__.py
odoo/addons/crm_phonecall_timesheet/__manifest__.py
odoo/addons/crm_phonecall_timesheet/i18n/crm_phonecall_timesheet.pot
odoo/addons/crm_phonecall_timesheet/i18n/cs_CZ.po
odoo/addons/crm_phonecall_timesheet/i18n/de.po
odoo/addons/crm_phonecall_timesheet/i18n/es.po
odoo/addons/crm_phonecall_timesheet/i18n/fr.po
odoo/addons/crm_phonecall_timesheet/i18n/it.po
odoo/addons/crm_phonecall_timesheet/i18n/nl_NL.po
odoo/addons/crm_phonecall_timesheet/i18n/pt.po
odoo/addons/crm_phonecall_timesheet/i18n/pt_BR.po
odoo/addons/crm_phonecall_timesheet/models/__init__.py
odoo/addons/crm_phonecall_timesheet/models/account_analytic_line.py
odoo/addons/crm_phonecall_timesheet/models/crm_phonecall.py
odoo/addons/crm_phonecall_timesheet/readme/CONFIGURE.rst
odoo/addons/crm_phonecall_timesheet/readme/CONTRIBUTORS.rst
odoo/addons/crm_phonecall_timesheet/readme/DESCRIPTION.rst
odoo/addons/crm_phonecall_timesheet/readme/ROADMAP.rst
odoo/addons/crm_phonecall_timesheet/readme/USAGE.rst
odoo/addons/crm_phonecall_timesheet/static/description/icon.png
odoo/addons/crm_phonecall_timesheet/static/description/index.html
odoo/addons/crm_phonecall_timesheet/tests/__init__.py
odoo/addons/crm_phonecall_timesheet/tests/test_crm_phonecall.py
odoo/addons/crm_phonecall_timesheet/views/crm_phonecall_view.xml
odoo/addons/crm_phonecall_timesheet/views/hr_timesheet_view.xml
odoo12_addon_crm_phonecall_timesheet-12.0.1.0.0.99.dev17.dist-info/METADATA
odoo12_addon_crm_phonecall_timesheet-12.0.1.0.0.99.dev17.dist-info/WHEEL
odoo12_addon_crm_phonecall_timesheet-12.0.1.0.0.99.dev17.dist-info/top_level.txt
odoo12_addon_crm_phonecall_timesheet-12.0.1.0.0.99.dev17.dist-info/RECORD
